falcon_sandbox/__init__.py
falcon_sandbox/cli.py
falcon_sandbox/helpers.py
falcon_sandbox-2.1.0.dist-info/LICENSE
falcon_sandbox-2.1.0.dist-info/METADATA
falcon_sandbox-2.1.0.dist-info/WHEEL
falcon_sandbox-2.1.0.dist-info/entry_points.txt
falcon_sandbox-2.1.0.dist-info/top_level.txt
falcon_sandbox-2.1.0.dist-info/RECORD
