Metadata-Version: 2.1
Name: falcon-sandbox
Version: 2.1.0
Summary: Python client library and command line tool for the [Falcon Sandbox API](https://www.crowdstrike.com/products/threat-intelligence/falcon-sandbox-malware-analysis/).
Author: John Davison & Sean McFeely
Author-email: Sean McFeely <mcfeelynaes@gmail.com>
Maintainer-email: Kien Pham <kienpham16496@gmail.com>, Sean McFeely <mcfeelynaes@gmail.com>
License: Apache-2.0
Project-URL: Homepage, https://github.com/ace-ecosystem/falcon-sandbox
Project-URL: Bug Tracker, https://github.com/ace-ecosystem/falcon-sandbox/issues
Keywords: Information Security,Malware Analysis
Classifier: Development Status :: 5 - Production/Stable
Classifier: Intended Audience :: Developers
Classifier: Intended Audience :: Information Technology
Classifier: Intended Audience :: Telecommunications Industry
Classifier: Operating System :: OS Independent
Classifier: License :: OSI Approved :: Apache Software License
Classifier: Programming Language :: Python :: 3 :: Only
Classifier: Programming Language :: Python :: 3.6
Classifier: Programming Language :: Python :: 3.7
Classifier: Programming Language :: Python :: 3.8
Classifier: Programming Language :: Python :: 3.9
Classifier: Programming Language :: Python :: 3.10
Requires-Python: >=3.0
License-File: LICENSE
Requires-Dist: crowdstrike-falconpy
Requires-Dist: coloredlogs
